claude_transcriber/__init__.py
claude_transcriber-0.2.1.dist-info/licenses/LICENSE
claude_transcriber-0.2.1.dist-info/METADATA
claude_transcriber-0.2.1.dist-info/WHEEL
claude_transcriber-0.2.1.dist-info/entry_points.txt
claude_transcriber-0.2.1.dist-info/top_level.txt
claude_transcriber-0.2.1.dist-info/RECORD
