Metadata-Version: 2.4
Name: claude-transcriber
Version: 0.2.1
Summary: Transcribe Claude Code JSONL logs to human-readable text
Author-email: Tom Yeh <tom@eumemic.com>
License: MIT
Project-URL: Homepage, https://github.com/eumemic/claude-transcriber
Project-URL: Repository, https://github.com/eumemic/claude-transcriber
Keywords: claude,anthropic,transcription,logs
Classifier: Development Status :: 4 - Beta
Classifier: Intended Audience :: Developers
Classifier: License :: OSI Approved :: MIT License
Classifier: Programming Language :: Python :: 3
Classifier: Programming Language :: Python :: 3.10
Classifier: Programming Language :: Python :: 3.11
Classifier: Programming Language :: Python :: 3.12
Requires-Python: >=3.10
License-File: LICENSE
Dynamic: license-file
